forestopenfermion/__init__.py
forestopenfermion/pyquil_circuit_generator.py
forestopenfermion/pyquil_connector.py
forestopenfermion/tests/__init__.py
forestopenfermion/tests/pyquil_connector_test.py
forestopenfermion/tests/pyquil_generator_test.py
forestopenfermion-0.0.2.dist-info/DESCRIPTION.rst
forestopenfermion-0.0.2.dist-info/METADATA
forestopenfermion-0.0.2.dist-info/RECORD
forestopenfermion-0.0.2.dist-info/WHEEL
forestopenfermion-0.0.2.dist-info/metadata.json
forestopenfermion-0.0.2.dist-info/top_level.txt
