Metadata-Version: 2.0
Name: forestopenfermion
Version: 0.0.2
Summary: A plugin allowing OpenFermion to interface with Forest.
Home-page: UNKNOWN
Author: Rigetti Computing
Author-email: softapps@rigetti.com
License: Apache 2
Platform: UNKNOWN
Requires-Dist: scipy (>=0.18.0)
Requires-Dist: numpy (>=1.11.0)
Requires-Dist: openfermion (==0.1a0)
Requires-Dist: pyquil (>=1.1.0)
Requires-Dist: future
